scrapy_feedexporter_azure_blob_3/__init__.py
scrapy_feedexporter_azure_blob_3-0.4.dist-info/METADATA
scrapy_feedexporter_azure_blob_3-0.4.dist-info/WHEEL
scrapy_feedexporter_azure_blob_3-0.4.dist-info/top_level.txt
scrapy_feedexporter_azure_blob_3-0.4.dist-info/RECORD
