Metadata-Version: 2.1
Name: scrapy-feedexporter-azure-blob-3
Version: 0.4
Summary: Scrapy extension Feed Exporter Storage Backend to export items to a Azure blob container
Home-page: https://github.com/StatRecovery/scrapy-feedexporter-azure-blob_3
Author: Matt Keegan
Author-email: matt@statrecovery.com
License: MIT
Platform: UNKNOWN
Classifier: Framework :: Scrapy
Classifier: Development Status :: 3 - Alpha
Classifier: Environment :: Console
Classifier: Intended Audience :: Developers
Classifier: License :: OSI Approved :: BSD License
Classifier: Operating System :: OS Independent
Classifier: Programming Language :: Python
Classifier: Programming Language :: Python :: 2
Classifier: Programming Language :: Python :: 2.7
Classifier: Programming Language :: Python :: 3
Classifier: Topic :: Utilities
Classifier: Framework :: Scrapy
Requires-Dist: azure-storage-blob
